odoo/addons/shift_worker_status/README.rst
odoo/addons/shift_worker_status/__init__.py
odoo/addons/shift_worker_status/__manifest__.py
odoo/addons/shift_worker_status/post_init.py
odoo/addons/shift_worker_status/rename_beesdoo.py
odoo/addons/shift_worker_status/data/data.xml
odoo/addons/shift_worker_status/demo/tasks.xml
odoo/addons/shift_worker_status/i18n/shift_worker_status.pot
odoo/addons/shift_worker_status/models/__init__.py
odoo/addons/shift_worker_status/models/cooperative_status.py
odoo/addons/shift_worker_status/models/res_config_settings.py
odoo/addons/shift_worker_status/models/shift_shift.py
odoo/addons/shift_worker_status/readme/CONTRIBUTORS.rst
odoo/addons/shift_worker_status/readme/DESCRIPTION.rst
odoo/addons/shift_worker_status/readme/HISTORY.rst
odoo/addons/shift_worker_status/tests/__init__.py
odoo/addons/shift_worker_status/tests/test_shift.py
odoo/addons/shift_worker_status/views/res_config_settings_view.xml
odoo12_addon_shift_worker_status-12.0.2.0.0.99.dev2.dist-info/METADATA
odoo12_addon_shift_worker_status-12.0.2.0.0.99.dev2.dist-info/WHEEL
odoo12_addon_shift_worker_status-12.0.2.0.0.99.dev2.dist-info/top_level.txt
odoo12_addon_shift_worker_status-12.0.2.0.0.99.dev2.dist-info/RECORD
